parse_broken_json/__init__.py
parse_broken_json-0.2.dist-info/LICENSE
parse_broken_json-0.2.dist-info/METADATA
parse_broken_json-0.2.dist-info/WHEEL
parse_broken_json-0.2.dist-info/top_level.txt
parse_broken_json-0.2.dist-info/RECORD
