Metadata-Version: 2.1
Name: parse-broken-json
Version: 0.2
Summary: Library to help parsing broken and invalid JSON.
Author-email: "Carlos A. Planchón" <carlosandresplanchonprestes@gmail.com>
License: MIT License
Project-URL: repository, https://github.com/carlosplanchon/parse_broken_json.git
Keywords: parsing,broken,json,invalid
Classifier: Intended Audience :: Developers
Classifier: Topic :: Software Development :: Build Tools
Classifier: License :: OSI Approved :: MIT License
Classifier: Programming Language :: Python :: 3.11
License-File: LICENSE
Requires-Dist: ijson
